Workbook

Sheet Setup
B2: Carbonara meal setup
B4: Setting | C4: Value | D4: Guidance
B5: Base recipe servings | C5: 2 | D5: Recipe quantities are defined for 2 servings.
B6: Desired servings | C6: 6 | D6: Editable input: enter a whole number from 1 to 20.
B7: Shopping budget (USD) | C7: 20 | D7: Editable input: enter an amount of zero or more.
B10: Using this workbook
B11: Amber cells are editable inputs. Update servings and budget above.
B12: Edit recipe quantities, stock, package sizes and prices in the Ingredients table.
B13: ShoppingList shows whole packages to buy and stock remaining after cooking.
B14: Dashboard summarizes ingredient use, shopping costs and budget status.

Sheet Ingredients
B2: Carbonara ingredients
B3: Source: user-provided illustrative quantities and package prices (USD).
B4: All quantities are grams. Egg yolks exclude shells and egg whites. Amber cells are editable.
B6: Ingredient | C6: Base quantity for 2 servings (g) | D6: Stock available (g) | E6: Package size (g) | F6: Package price (USD) | G6: Required quantity (g) | H6: Used-ingredient cost (USD)
B7: Spaghetti (dry) | C7: 200 | D7: 100 | E7: 500 | F7: 2.5 | G7: =C7*Setup!$C$6/Setup!$C$5 -> 600 | H7: =G7/E7*F7 -> 3
B8: Guanciale | C8: 80 | D8: 20 | E8: 100 | F8: 4 | G8: =C8*Setup!$C$6/Setup!$C$5 -> 240 | H8: =G8/E8*F8 -> 9.6
B9: Egg yolks | C9: 36 | D9: 0 | E9: 36 | F9: 0.54 | G9: =C9*Setup!$C$6/Setup!$C$5 -> 108 | H9: =G9/E9*F9 -> 1.62
B10: Pecorino Romano | C10: 40 | D10: 10 | E10: 100 | F10: 3.5 | G10: =C10*Setup!$C$6/Setup!$C$5 -> 120 | H10: =G10/E10*F10 -> 4.2
B11: Black pepper | C11: 1 | D11: 2 | E11: 50 | F11: 2.5 | G11: =C11*Setup!$C$6/Setup!$C$5 -> 3 | H11: =G11/E11*F11 -> 0.15
B14: Used-ingredient cost values all required ingredients at their package unit price, including ingredients from stock.

Sheet ShoppingList
B2: Carbonara shopping list
B3: Highlighted rows need a purchase. Zero-purchase ingredients remain listed.
B4: Desired servings | C4: =Setup!C6 -> 6 | E4: Budget (USD) | G4: =Setup!C7 -> 20
B6: Ingredient | C6: Required quantity (g) | D6: Stock available (g) | E6: Additional needed (g) | F6: Package size (g) | G6: Package price (USD) | H6: Whole packages to buy | I6: Purchase cost (USD) | J6: Stock after cooking (g) | K6: Used-ingredient cost (USD)
B7: =Ingredients!B7 -> Spaghetti (dry) | C7: =Ingredients!G7 -> 600 | D7: =Ingredients!D7 -> 100 | E7: =MAX(C7-D7,0) -> 500 | F7: =Ingredients!E7 -> 500 | G7: =Ingredients!F7 -> 2.5 | H7: =ROUNDUP(E7/F7,0) -> 1 | I7: =H7*G7 -> 2.5 | J7: =D7+H7*F7-C7 -> 0 | K7: =Ingredients!H7 -> 3
B8: =Ingredients!B8 -> Guanciale | C8: =Ingredients!G8 -> 240 | D8: =Ingredients!D8 -> 20 | E8: =MAX(C8-D8,0) -> 220 | F8: =Ingredients!E8 -> 100 | G8: =Ingredients!F8 -> 4 | H8: =ROUNDUP(E8/F8,0) -> 3 | I8: =H8*G8 -> 12 | J8: =D8+H8*F8-C8 -> 80 | K8: =Ingredients!H8 -> 9.6
B9: =Ingredients!B9 -> Egg yolks | C9: =Ingredients!G9 -> 108 | D9: =Ingredients!D9 -> 0 | E9: =MAX(C9-D9,0) -> 108 | F9: =Ingredients!E9 -> 36 | G9: =Ingredients!F9 -> 0.54 | H9: =ROUNDUP(E9/F9,0) -> 3 | I9: =H9*G9 -> 1.62 | J9: =D9+H9*F9-C9 -> 0 | K9: =Ingredients!H9 -> 1.62
B10: =Ingredients!B10 -> Pecorino Romano | C10: =Ingredients!G10 -> 120 | D10: =Ingredients!D10 -> 10 | E10: =MAX(C10-D10,0) -> 110 | F10: =Ingredients!E10 -> 100 | G10: =Ingredients!F10 -> 3.5 | H10: =ROUNDUP(E10/F10,0) -> 2 | I10: =H10*G10 -> 7 | J10: =D10+H10*F10-C10 -> 90 | K10: =Ingredients!H10 -> 4.2
B11: =Ingredients!B11 -> Black pepper | C11: =Ingredients!G11 -> 3 | D11: =Ingredients!D11 -> 2 | E11: =MAX(C11-D11,0) -> 1 | F11: =Ingredients!E11 -> 50 | G11: =Ingredients!F11 -> 2.5 | H11: =ROUNDUP(E11/F11,0) -> 1 | I11: =H11*G11 -> 2.5 | J11: =D11+H11*F11-C11 -> 49 | K11: =Ingredients!H11 -> 0.15
B13: Total cost (USD) | I13: =SUM(I7:I11) -> 25.62 | K13: =SUM(K7:K11) -> 18.57
B16: Purchase cost is the cash needed for whole packages. Stock after cooking includes unused portions of those packages.

Sheet Dashboard
B2: Carbonara cost dashboard
B4: Meal cost | C4: Value | E4: Shopping budget | F4: Value
B5: Desired servings | C5: =Setup!C6 -> 6 | E5: Total purchase cost (USD) | F5: =ShoppingList!I13 -> 25.62
B6: Used-ingredient cost (USD) | C6: =ShoppingList!K13 -> 18.57 | E6: Budget (USD) | F6: =Setup!C7 -> 20
B7: Used cost per serving (USD) | C7: =ROUND(ROUND(C6/C5,10),2) -> 3.1 | E7: Budget remaining (USD) | F7: =F6-F5 -> -5.62
E9: Budget status | F9: =IF(F5<=F6,"Within budget","Over budget") -> Over budget
