Workbook

Sheet Setup
A2: Risotto meal planner
A3: Edit the amber cells to update the plan.
A5: Setting | B5: Value
A6: Base recipe servings | B6: 2 | D6: Recipe quantities are based on 2 servings.
A7: Desired servings | B7: 6 | D7: Choose 1 to 20 whole servings.
A8: Shopping budget (USD) | B8: 20 | D8: Budget applies to whole-package purchases.
A11: How costs are calculated
A12: Used-ingredient cost | B12: Value of all ingredients used, including stock.
A13: Purchase cost | B13: Cash needed for whole packages after using stock.
A16: All quantities are grams. Egg yolks exclude shells and egg whites.

Sheet Ingredients
A2: Ingredients
A3: Source: user-provided illustrative data. Amber cells are editable. All quantities are grams.
A5: Ingredient | B5: Base quantity (g) | C5: Stock available (g) | D5: Package size (g) | E5: Package price (USD) | F5: Required quantity (g) | G5: Used-ingredient cost (USD)
A6: Spaghetti (dry) | B6: 200 | C6: 100 | D6: 500 | E6: 2.5 | F6: =B6*Setup!$B$7/Setup!$B$6 -> 600 | G6: =F6/D6*E6 -> 3
A7: Guanciale | B7: 80 | C7: 20 | D7: 100 | E7: 4 | F7: =B7*Setup!$B$7/Setup!$B$6 -> 240 | G7: =F7/D7*E7 -> 9.6
A8: Egg yolks | B8: 36 | C8: 0 | D8: 36 | E8: 0.54 | F8: =B8*Setup!$B$7/Setup!$B$6 -> 108 | G8: =F8/D8*E8 -> 1.62
A9: Pecorino Romano | B9: 40 | C9: 10 | D9: 100 | E9: 3.5 | F9: =B9*Setup!$B$7/Setup!$B$6 -> 120 | G9: =F9/D9*E9 -> 4.2
A10: Black pepper | B10: 1 | C10: 2 | D10: 50 | E10: 2.5 | F10: =B10*Setup!$B$7/Setup!$B$6 -> 3 | G10: =F10/D10*E10 -> 0.15
A12: Base quantities serve 2. Egg yolks are weighed without shells or egg whites.
A13: Used cost = required quantity / package size × package price.

Sheet ShoppingList
A2: Shopping list
A3: Desired servings | B3: =Setup!B7 -> 6 | D3: Amber rows require a purchase. Quantities are grams. | I3: Budget (USD) | J3: =Setup!B8 -> 20
A5: Ingredient | B5: Required (g) | C5: Stock (g) | D5: Additional needed (g) | E5: Package size (g) | F5: Package price (USD) | G5: Packages to buy | H5: Purchase cost (USD) | I5: Stock after cooking (g) | J5: Used-ingredient cost (USD)
A6: =Ingredients!A6 -> Spaghetti (dry) | B6: =Ingredients!F6 -> 600 | C6: =Ingredients!C6 -> 100 | D6: =MAX(B6-C6,0) -> 500 | E6: =Ingredients!D6 -> 500 | F6: =Ingredients!E6 -> 2.5 | G6: =ROUNDUP(D6/E6,0) -> 1 | H6: =G6*F6 -> 2.5 | I6: =C6+G6*E6-B6 -> 0 | J6: =Ingredients!G6 -> 3
A7: =Ingredients!A7 -> Guanciale | B7: =Ingredients!F7 -> 240 | C7: =Ingredients!C7 -> 20 | D7: =MAX(B7-C7,0) -> 220 | E7: =Ingredients!D7 -> 100 | F7: =Ingredients!E7 -> 4 | G7: =ROUNDUP(D7/E7,0) -> 3 | H7: =G7*F7 -> 12 | I7: =C7+G7*E7-B7 -> 80 | J7: =Ingredients!G7 -> 9.6
A8: =Ingredients!A8 -> Egg yolks | B8: =Ingredients!F8 -> 108 | C8: =Ingredients!C8 -> 0 | D8: =MAX(B8-C8,0) -> 108 | E8: =Ingredients!D8 -> 36 | F8: =Ingredients!E8 -> 0.54 | G8: =ROUNDUP(D8/E8,0) -> 3 | H8: =G8*F8 -> 1.62 | I8: =C8+G8*E8-B8 -> 0 | J8: =Ingredients!G8 -> 1.62
A9: =Ingredients!A9 -> Pecorino Romano | B9: =Ingredients!F9 -> 120 | C9: =Ingredients!C9 -> 10 | D9: =MAX(B9-C9,0) -> 110 | E9: =Ingredients!D9 -> 100 | F9: =Ingredients!E9 -> 3.5 | G9: =ROUNDUP(D9/E9,0) -> 2 | H9: =G9*F9 -> 7 | I9: =C9+G9*E9-B9 -> 90 | J9: =Ingredients!G9 -> 4.2
A10: =Ingredients!A10 -> Black pepper | B10: =Ingredients!F10 -> 3 | C10: =Ingredients!C10 -> 2 | D10: =MAX(B10-C10,0) -> 1 | E10: =Ingredients!D10 -> 50 | F10: =Ingredients!E10 -> 2.5 | G10: =ROUNDUP(D10/E10,0) -> 1 | H10: =G10*F10 -> 2.5 | I10: =C10+G10*E10-B10 -> 49 | J10: =Ingredients!G10 -> 0.15
A12: TOTAL | H12: =SUM(H6:H10) -> 25.62 | J12: =SUM(J6:J10) -> 18.57
A14: Packages are rounded up. Stock after cooking = stock + packages bought × package size − required quantity.

Sheet Dashboard
A2: Risotto cost dashboard
A3: Change servings and budget on Setup. Update stock and package prices on Ingredients.
A5: Desired servings | B5: =Setup!B7 -> 6
A6: Total used-ingredient cost | B6: =ShoppingList!J12 -> 18.57
A7: Used cost per serving | B7: =ROUND(B6/B5,10) -> 3.095
A8: Total purchase cost | B8: =ShoppingList!H12 -> 25.62
A9: Shopping budget | B9: =Setup!B8 -> 20
A10: Budget remaining | B10: =B9-B8 -> -5.62
A11: Budget status | B11: =IF(B8<=B9,"Within budget","Over budget") -> Over budget
